{"chunk_definitions":[{"row":9,"row_count":1,"visible":true,"expansion_state":0,"options":{"engine":"r","label":"unnamed-chunk-1"},"document_id":"349ED18F","chunk_id":"cu5x8drfbfj3p","chunk_label":"unnamed-chunk-1"},{"row":17,"row_count":1,"visible":true,"expansion_state":0,"options":{},"document_id":"349ED18F","chunk_id":"c3fm0s21c2obi","chunk_label":"unnamed-chunk-2"},{"row":29,"row_count":1,"visible":true,"expansion_state":0,"options":{"engine":"r","label":"unnamed-chunk-4"},"document_id":"349ED18F","chunk_id":"cht48msx5cbps","chunk_label":"unnamed-chunk-4"},{"row":37,"row_count":1,"visible":true,"expansion_state":0,"options":{"engine":"r","label":"unnamed-chunk-2"},"document_id":"349ED18F","chunk_id":"clbcv3qtiziyy","chunk_label":"unnamed-chunk-5"},{"row":58,"row_count":1,"visible":true,"expansion_state":0,"options":{"engine":"r","label":"unnamed-chunk-10"},"document_id":"349ED18F","chunk_id":"cqeb5831xymhp","chunk_label":"unnamed-chunk-6"},{"row":65,"row_count":1,"visible":true,"expansion_state":0,"options":{"engine":"r","label":"unnamed-chunk-23"},"document_id":"349ED18F","chunk_id":"c0uay5jl7bboc","chunk_label":"unnamed-chunk-7"},{"row":74,"row_count":1,"visible":true,"expansion_state":0,"options":{"engine":"r","label":"unnamed-chunk-24"},"document_id":"349ED18F","chunk_id":"caczekhjwurfw","chunk_label":"unnamed-chunk-8"},{"row":79,"row_count":1,"visible":true,"expansion_state":0,"options":{"engine":"r","label":"unnamed-chunk-25"},"document_id":"349ED18F","chunk_id":"cknffyyp8hdlg","chunk_label":"unnamed-chunk-9"},{"row":85,"row_count":1,"visible":true,"expansion_state":0,"options":{"engine":"r","label":"unnamed-chunk-26"},"document_id":"349ED18F","chunk_id":"czvzvw6bnv79i","chunk_label":"unnamed-chunk-10"},{"row":103,"row_count":1,"visible":true,"expansion_state":0,"options":{"engine":"r","label":"unnamed-chunk-27"},"document_id":"349ED18F","chunk_id":"cv60k1uut3ppx","chunk_label":"unnamed-chunk-11"},{"row":125,"row_count":1,"visible":true,"expansion_state":0,"options":{"engine":"r","label":"unnamed-chunk-3"},"document_id":"349ED18F","chunk_id":"coy7uur5xpx93","chunk_label":"unnamed-chunk-12"},{"row":129,"row_count":1,"visible":true,"expansion_state":0,"options":{"engine":"r","label":"unnamed-chunk-6"},"document_id":"349ED18F","chunk_id":"chpzu7sjr9j87","chunk_label":"unnamed-chunk-13"},{"row":133,"row_count":1,"visible":true,"expansion_state":0,"options":{"engine":"r","label":"unnamed-chunk-7"},"document_id":"349ED18F","chunk_id":"ctrzd0d9o9tlj","chunk_label":"unnamed-chunk-14"},{"row":140,"row_count":1,"visible":true,"expansion_state":0,"options":{"engine":"r","label":"unnamed-chunk-10"},"document_id":"349ED18F","chunk_id":"cdiikx7gar3k1","chunk_label":"unnamed-chunk-15"},{"row":147,"row_count":1,"visible":true,"expansion_state":0,"options":{"engine":"r","label":"unnamed-chunk-11"},"document_id":"349ED18F","chunk_id":"cuxym9h7j1qwc","chunk_label":"unnamed-chunk-16"},{"row":156,"row_count":1,"visible":true,"expansion_state":0,"options":{"engine":"r","label":"unnamed-chunk-12"},"document_id":"349ED18F","chunk_id":"ciam9et0rr7tp","chunk_label":"unnamed-chunk-17"},{"row":182,"row_count":1,"visible":true,"expansion_state":0,"options":{"engine":"r","label":"unnamed-chunk-13"},"document_id":"349ED18F","chunk_id":"c9n86j6n3penx","chunk_label":"unnamed-chunk-19"},{"row":186,"row_count":1,"visible":true,"expansion_state":0,"options":{"engine":"r","label":"unnamed-chunk-14"},"document_id":"349ED18F","chunk_id":"cquermulwn2dn","chunk_label":"unnamed-chunk-20"},{"row":202,"row_count":1,"visible":true,"expansion_state":0,"options":{"engine":"r","label":"unnamed-chunk-16"},"document_id":"349ED18F","chunk_id":"c5195ysxmkfnh","chunk_label":"unnamed-chunk-22"},{"row":217,"row_count":1,"visible":true,"expansion_state":0,"options":{"engine":"r","label":"unnamed-chunk-17"},"document_id":"349ED18F","chunk_id":"c2ghz12dw6ir8","chunk_label":"unnamed-chunk-23"},{"row":221,"row_count":1,"visible":true,"expansion_state":0,"options":{"engine":"r","label":"unnamed-chunk-19"},"document_id":"349ED18F","chunk_id":"cz04o6okbkroo","chunk_label":"unnamed-chunk-24"},{"row":229,"row_count":1,"visible":true,"expansion_state":0,"options":{"engine":"r","label":"unnamed-chunk-6"},"document_id":"349ED18F","chunk_id":"c8wza84w6smqx","chunk_label":"unnamed-chunk-25"},{"row":233,"row_count":1,"visible":true,"expansion_state":0,"options":{"engine":"r","label":"unnamed-chunk-8"},"document_id":"349ED18F","chunk_id":"cwx8dq6luxd7y","chunk_label":"unnamed-chunk-26"},{"row":242,"row_count":1,"visible":true,"expansion_state":0,"options":{"engine":"r","label":"unnamed-chunk-9"},"document_id":"349ED18F","chunk_id":"cim7i73vmwtzp","chunk_label":"unnamed-chunk-27"},{"row":251,"row_count":1,"visible":true,"expansion_state":0,"options":{"engine":"r","label":"unnamed-chunk-27"},"document_id":"349ED18F","chunk_id":"cl3u1k7zwrmfg","chunk_label":"unnamed-chunk-28"},{"row":255,"row_count":1,"visible":true,"expansion_state":0,"options":{"engine":"r","label":"unnamed-chunk-28"},"document_id":"349ED18F","chunk_id":"c976blw92kk4r","chunk_label":"unnamed-chunk-29"},{"row":259,"row_count":1,"visible":true,"expansion_state":0,"options":{"engine":"r","label":"unnamed-chunk-29"},"document_id":"349ED18F","chunk_id":"cwrff7xgktyed","chunk_label":"unnamed-chunk-30"},{"row":263,"row_count":1,"visible":true,"expansion_state":0,"options":{"engine":"r","label":"unnamed-chunk-30"},"document_id":"349ED18F","chunk_id":"cdkankl0xhzt3","chunk_label":"unnamed-chunk-31"},{"row":270,"row_count":1,"visible":true,"expansion_state":0,"options":{"engine":"r","label":"unnamed-chunk-31"},"document_id":"349ED18F","chunk_id":"cwyzpbzy4zyyf","chunk_label":"unnamed-chunk-32"},{"row":274,"row_count":1,"visible":true,"expansion_state":0,"options":{"engine":"r","label":"unnamed-chunk-48"},"document_id":"349ED18F","chunk_id":"c6hgoenux5kwq","chunk_label":"unnamed-chunk-33"},{"row":277,"row_count":1,"visible":true,"expansion_state":0,"options":{"engine":"r","label":"unnamed-chunk-49"},"document_id":"349ED18F","chunk_id":"c3coe03sqqfd8","chunk_label":"unnamed-chunk-34"},{"row":291,"row_count":1,"visible":true,"expansion_state":0,"options":{"engine":"r","label":"unnamed-chunk-52"},"document_id":"349ED18F","chunk_id":"c4r4emfq3jkt7","chunk_label":"unnamed-chunk-36"},{"row":295,"row_count":1,"visible":true,"expansion_state":0,"options":{"engine":"r","label":"unnamed-chunk-51"},"document_id":"349ED18F","chunk_id":"cko00savtm680","chunk_label":"unnamed-chunk-37"},{"row":300,"row_count":1,"visible":true,"expansion_state":0,"options":{"engine":"r","label":"unnamed-chunk-54"},"document_id":"349ED18F","chunk_id":"cqzp7vx90f5t2","chunk_label":"unnamed-chunk-38"},{"row":312,"row_count":1,"visible":true,"expansion_state":0,"options":{"engine":"r","label":"unnamed-chunk-55"},"document_id":"349ED18F","chunk_id":"cd68uww1u33yi","chunk_label":"unnamed-chunk-39"},{"row":325,"row_count":1,"visible":true,"expansion_state":0,"options":{"engine":"r","label":"unnamed-chunk-58"},"document_id":"349ED18F","chunk_id":"cugxhlvlx4djg","chunk_label":"unnamed-chunk-41"},{"row":332,"row_count":1,"visible":true,"expansion_state":0,"options":{"engine":"r","label":"unnamed-chunk-59"},"document_id":"349ED18F","chunk_id":"coc2pz7sealqy","chunk_label":"unnamed-chunk-42"},{"row":337,"row_count":1,"visible":true,"expansion_state":0,"options":{"engine":"r","label":"unnamed-chunk-62"},"document_id":"349ED18F","chunk_id":"cr138czhhahku","chunk_label":"unnamed-chunk-43"},{"row":343,"row_count":1,"visible":true,"expansion_state":0,"options":{"engine":"r","label":"unnamed-chunk-63"},"document_id":"349ED18F","chunk_id":"cp5d1jso95i9j","chunk_label":"unnamed-chunk-44"},{"row":347,"row_count":1,"visible":true,"expansion_state":0,"options":{"engine":"r","label":"unnamed-chunk-64"},"document_id":"349ED18F","chunk_id":"ce168t5vc8yu7","chunk_label":"unnamed-chunk-45"},{"row":351,"row_count":1,"visible":true,"expansion_state":0,"options":{"engine":"r","label":"unnamed-chunk-65"},"document_id":"349ED18F","chunk_id":"c6ed676i6khc3","chunk_label":"unnamed-chunk-46"},{"row":355,"row_count":1,"visible":true,"expansion_state":0,"options":{"engine":"r","label":"unnamed-chunk-66"},"document_id":"349ED18F","chunk_id":"cq243ljhh4tw3","chunk_label":"unnamed-chunk-47"},{"row":361,"row_count":1,"visible":true,"expansion_state":0,"options":{"engine":"r","label":"unnamed-chunk-68"},"document_id":"349ED18F","chunk_id":"cmrfkmzlpeh8q","chunk_label":"unnamed-chunk-48"},{"row":365,"row_count":1,"visible":true,"expansion_state":0,"options":{"engine":"r","label":"unnamed-chunk-69"},"document_id":"349ED18F","chunk_id":"cjea56ihoqme0","chunk_label":"unnamed-chunk-49"},{"row":369,"row_count":1,"visible":true,"expansion_state":0,"options":{"engine":"r","label":"unnamed-chunk-70"},"document_id":"349ED18F","chunk_id":"c17981e1xx40k","chunk_label":"unnamed-chunk-50"},{"row":373,"row_count":1,"visible":true,"expansion_state":0,"options":{"engine":"r","label":"unnamed-chunk-71"},"document_id":"349ED18F","chunk_id":"coo2y3i4pc088","chunk_label":"unnamed-chunk-51"},{"row":377,"row_count":1,"visible":true,"expansion_state":0,"options":{"engine":"r","label":"unnamed-chunk-73"},"document_id":"349ED18F","chunk_id":"cpwxiclkivu0j","chunk_label":"unnamed-chunk-52"},{"row":385,"row_count":1,"visible":true,"expansion_state":0,"options":{"engine":"r","label":"unnamed-chunk-76"},"document_id":"349ED18F","chunk_id":"cad2ucn1uaen6","chunk_label":"unnamed-chunk-54"},{"row":389,"row_count":1,"visible":true,"expansion_state":0,"options":{"engine":"r","label":"unnamed-chunk-77"},"document_id":"349ED18F","chunk_id":"cz3an50d55872","chunk_label":"unnamed-chunk-55"},{"row":395,"row_count":1,"visible":true,"expansion_state":0,"options":{"engine":"r","label":"unnamed-chunk-81"},"document_id":"349ED18F","chunk_id":"cayotszlpzcuz","chunk_label":"unnamed-chunk-56"},{"row":399,"row_count":1,"visible":true,"expansion_state":0,"options":{"engine":"r","label":"unnamed-chunk-83"},"document_id":"349ED18F","chunk_id":"c1pza10h2rsub","chunk_label":"unnamed-chunk-57"},{"row":402,"row_count":1,"visible":true,"expansion_state":0,"options":{"engine":"r","label":"unnamed-chunk-84"},"document_id":"349ED18F","chunk_id":"cwosbw6tv0mw4","chunk_label":"unnamed-chunk-58"},{"row":406,"row_count":1,"visible":true,"expansion_state":0,"options":{"engine":"r","label":"unnamed-chunk-86"},"document_id":"349ED18F","chunk_id":"cdm1knptd8rhj","chunk_label":"unnamed-chunk-59"},{"row":409,"row_count":1,"visible":true,"expansion_state":0,"options":{"engine":"r","label":"unnamed-chunk-87"},"document_id":"349ED18F","chunk_id":"c8ln29n0mfoo1","chunk_label":"unnamed-chunk-60"},{"row":413,"row_count":1,"visible":true,"expansion_state":0,"options":{"engine":"r","label":"unnamed-chunk-91"},"document_id":"349ED18F","chunk_id":"csq49g01d8hvd","chunk_label":"unnamed-chunk-61"},{"row":418,"row_count":1,"visible":true,"expansion_state":0,"options":{"engine":"r","label":"unnamed-chunk-92"},"document_id":"349ED18F","chunk_id":"cvd87tr6cxtd5","chunk_label":"unnamed-chunk-62"},{"row":422,"row_count":1,"visible":true,"expansion_state":0,"options":{"engine":"r","label":"unnamed-chunk-93"},"document_id":"349ED18F","chunk_id":"cujwh3mcksldu","chunk_label":"unnamed-chunk-63"},{"row":426,"row_count":1,"visible":true,"expansion_state":0,"options":{"engine":"r","label":"unnamed-chunk-94"},"document_id":"349ED18F","chunk_id":"cb5dxvyn2zvn1","chunk_label":"unnamed-chunk-64"}],"doc_write_time":1641164901}